<annotation>
	<folder>JPEGImages</folder>
	<filename>0 (134).jpg</filename>
	<path>C:\Users\LENOVO\Desktop\VOC2007\JPEGImages\0 (134).jpg</path>
	<source>
		<database>Unknown</database>
	</source>
	<size>
		<width>2560</width>
		<height>1440</height>
		<depth>3</depth>
	</size>
	<segmented>0</segmented>
	<object>
		<name>target</name>
		<pose>Unspecified</pose>
		<truncated>1</truncated>
		<difficult>0</difficult>
		<bndbox>
			<xmin>783</xmin>
			<ymin>1</ymin>
			<xmax>2151</xmax>
			<ymax>1117</ymax>
		</bndbox>
	</object>
	<object>
		<name>kernel</name>
		<pose>Unspecified</pose>
		<truncated>0</truncated>
		<difficult>0</difficult>
		<bndbox>
			<xmin>1464</xmin>
			<ymin>595</ymin>
			<xmax>1468</xmax>
			<ymax>597</ymax>
		</bndbox>
	</object>
	<object>
		<name>ten</name>
		<pose>Unspecified</pose>
		<truncated>0</truncated>
		<difficult>0</difficult>
		<bndbox>
			<xmin>1334</xmin>
			<ymin>463</ymin>
			<xmax>1608</xmax>
			<ymax>719</ymax>
		</bndbox>
	</object>
</annotation>
