<annotation>
	<folder>JPEGImages</folder>
	<filename>0 (114).jpg</filename>
	<path>C:\Users\LENOVO\Desktop\VOC2007\JPEGImages\0 (114).jpg</path>
	<source>
		<database>Unknown</database>
	</source>
	<size>
		<width>2560</width>
		<height>1440</height>
		<depth>3</depth>
	</size>
	<segmented>0</segmented>
	<object>
		<name>target</name>
		<pose>Unspecified</pose>
		<truncated>0</truncated>
		<difficult>0</difficult>
		<bndbox>
			<xmin>742</xmin>
			<ymin>5</ymin>
			<xmax>2198</xmax>
			<ymax>1176</ymax>
		</bndbox>
	</object>
	<object>
		<name>kernel</name>
		<pose>Unspecified</pose>
		<truncated>0</truncated>
		<difficult>0</difficult>
		<bndbox>
			<xmin>1461</xmin>
			<ymin>639</ymin>
			<xmax>1464</xmax>
			<ymax>641</ymax>
		</bndbox>
	</object>
	<object>
		<name>ten</name>
		<pose>Unspecified</pose>
		<truncated>0</truncated>
		<difficult>0</difficult>
		<bndbox>
			<xmin>1325</xmin>
			<ymin>502</ymin>
			<xmax>1612</xmax>
			<ymax>771</ymax>
		</bndbox>
	</object>
</annotation>
