<annotation>
	<folder>JPEGImages</folder>
	<filename>0 (272).jpg</filename>
	<path>C:\Users\LENOVO\Desktop\VOC2007\JPEGImages\0 (272).jpg</path>
	<source>
		<database>Unknown</database>
	</source>
	<size>
		<width>2560</width>
		<height>1440</height>
		<depth>3</depth>
	</size>
	<segmented>0</segmented>
	<object>
		<name>target</name>
		<pose>Unspecified</pose>
		<truncated>0</truncated>
		<difficult>0</difficult>
		<bndbox>
			<xmin>327</xmin>
			<ymin>5</ymin>
			<xmax>1895</xmax>
			<ymax>1297</ymax>
		</bndbox>
	</object>
	<object>
		<name>kernel</name>
		<pose>Unspecified</pose>
		<truncated>0</truncated>
		<difficult>0</difficult>
		<bndbox>
			<xmin>1117</xmin>
			<ymin>690</ymin>
			<xmax>1120</xmax>
			<ymax>693</ymax>
		</bndbox>
	</object>
	<object>
		<name>ten</name>
		<pose>Unspecified</pose>
		<truncated>0</truncated>
		<difficult>0</difficult>
		<bndbox>
			<xmin>971</xmin>
			<ymin>549</ymin>
			<xmax>1276</xmax>
			<ymax>822</ymax>
		</bndbox>
	</object>
</annotation>
