<annotation>
	<folder>JPEGImages</folder>
	<filename>ID_3-0154.jpg</filename>
	<path>C:\Users\LENOVO\Desktop\VOC2007\JPEGImages\ID_3-0154.jpg</path>
	<source>
		<database>Unknown</database>
	</source>
	<size>
		<width>1920</width>
		<height>1080</height>
		<depth>3</depth>
	</size>
	<segmented>0</segmented>
	<object>
		<name>hole</name>
		<pose>Unspecified</pose>
		<truncated>0</truncated>
		<difficult>0</difficult>
		<bndbox>
			<xmin>1198</xmin>
			<ymin>462</ymin>
			<xmax>1211</xmax>
			<ymax>474</ymax>
		</bndbox>
	</object>
	<object>
		<name>hole</name>
		<pose>Unspecified</pose>
		<truncated>0</truncated>
		<difficult>0</difficult>
		<bndbox>
			<xmin>864</xmin>
			<ymin>419</ymin>
			<xmax>878</xmax>
			<ymax>430</ymax>
		</bndbox>
	</object>
	<object>
		<name>hole</name>
		<pose>Unspecified</pose>
		<truncated>0</truncated>
		<difficult>0</difficult>
		<bndbox>
			<xmin>880</xmin>
			<ymin>492</ymin>
			<xmax>891</xmax>
			<ymax>500</ymax>
		</bndbox>
	</object>
	<object>
		<name>hole</name>
		<pose>Unspecified</pose>
		<truncated>0</truncated>
		<difficult>0</difficult>
		<bndbox>
			<xmin>896</xmin>
			<ymin>497</ymin>
			<xmax>910</xmax>
			<ymax>509</ymax>
		</bndbox>
	</object>
	<object>
		<name>hole</name>
		<pose>Unspecified</pose>
		<truncated>0</truncated>
		<difficult>0</difficult>
		<bndbox>
			<xmin>920</xmin>
			<ymin>505</ymin>
			<xmax>931</xmax>
			<ymax>518</ymax>
		</bndbox>
	</object>
	<object>
		<name>hole</name>
		<pose>Unspecified</pose>
		<truncated>0</truncated>
		<difficult>0</difficult>
		<bndbox>
			<xmin>890</xmin>
			<ymin>685</ymin>
			<xmax>901</xmax>
			<ymax>700</ymax>
		</bndbox>
	</object>
	<object>
		<name>hole</name>
		<pose>Unspecified</pose>
		<truncated>0</truncated>
		<difficult>0</difficult>
		<bndbox>
			<xmin>879</xmin>
			<ymin>719</ymin>
			<xmax>890</xmax>
			<ymax>732</ymax>
		</bndbox>
	</object>
	<object>
		<name>hole</name>
		<pose>Unspecified</pose>
		<truncated>0</truncated>
		<difficult>0</difficult>
		<bndbox>
			<xmin>1088</xmin>
			<ymin>776</ymin>
			<xmax>1101</xmax>
			<ymax>789</ymax>
		</bndbox>
	</object>
	<object>
		<name>target</name>
		<pose>Unspecified</pose>
		<truncated>1</truncated>
		<difficult>0</difficult>
		<bndbox>
			<xmin>623</xmin>
			<ymin>1</ymin>
			<xmax>1582</xmax>
			<ymax>801</ymax>
		</bndbox>
	</object>
	<object>
		<name>kernel</name>
		<pose>Unspecified</pose>
		<truncated>0</truncated>
		<difficult>0</difficult>
		<bndbox>
			<xmin>1098</xmin>
			<ymin>419</ymin>
			<xmax>1100</xmax>
			<ymax>424</ymax>
		</bndbox>
	</object>
	<object>
		<name>ten</name>
		<pose>Unspecified</pose>
		<truncated>0</truncated>
		<difficult>0</difficult>
		<bndbox>
			<xmin>1004</xmin>
			<ymin>329</ymin>
			<xmax>1199</xmax>
			<ymax>516</ymax>
		</bndbox>
	</object>
</annotation>
